aind_analysis_arch_result_access/__init__.py
aind_analysis_arch_result_access/df_mle_model_fitting.py
aind_analysis_arch_result_access/han_pipeline.py
aind_analysis_arch_result_access/patch/patch_20250213_migrate_database.py
aind_analysis_arch_result_access/patch/patch_20250922_redo_Bowen_sessions.py
aind_analysis_arch_result_access/util/__init__.py
aind_analysis_arch_result_access/util/reformat.py
aind_analysis_arch_result_access/util/s3.py
aind_analysis_arch_result_access-1.1.0.dist-info/licenses/LICENSE
aind_analysis_arch_result_access-1.1.0.dist-info/METADATA
aind_analysis_arch_result_access-1.1.0.dist-info/WHEEL
aind_analysis_arch_result_access-1.1.0.dist-info/top_level.txt
aind_analysis_arch_result_access-1.1.0.dist-info/RECORD
