Metadata-Version: 2.4
Name: aind-analysis-arch-result-access
Version: 1.1.0
Summary: Generated from aind-library-template
Author: Allen Institute for Neural Dynamics
Author-email: Han Hou <han.hou@alleninstitute.org>
License: MIT
Classifier: Programming Language :: Python :: 3
Requires-Python: >=3.9
License-File: LICENSE
Requires-Dist: s3fs
Requires-Dist: pandas
Requires-Dist: numpy
Requires-Dist: aind-data-access-api[docdb]
Requires-Dist: tqdm
Requires-Dist: scipy
Provides-Extra: dev
Requires-Dist: black; extra == "dev"
Requires-Dist: coverage; extra == "dev"
Requires-Dist: flake8; extra == "dev"
Requires-Dist: interrogate; extra == "dev"
Requires-Dist: isort; extra == "dev"
Requires-Dist: Sphinx; extra == "dev"
Requires-Dist: furo; extra == "dev"
Dynamic: license-file
